aiohttp_admin/__init__.py
aiohttp_admin/py.typed
aiohttp_admin/routes.py
aiohttp_admin/security.py
aiohttp_admin/types.py
aiohttp_admin/views.py
aiohttp_admin/backends/__init__.py
aiohttp_admin/backends/abc.py
aiohttp_admin/backends/sqlalchemy.py
aiohttp_admin/static/admin.js
aiohttp_admin/static/favicon.svg
aiohttp_admin/static/main.7a473ebf.js.map
aiohttp_admin-0.1.0a3.dist-info/LICENSE
aiohttp_admin-0.1.0a3.dist-info/METADATA
aiohttp_admin-0.1.0a3.dist-info/WHEEL
aiohttp_admin-0.1.0a3.dist-info/top_level.txt
aiohttp_admin-0.1.0a3.dist-info/RECORD
