Metadata-Version: 2.1
Name: aiohttp-admin
Version: 0.1.0a3
Summary: admin interface for aiohttp application
Home-page: https://github.com/aio-libs/aiohttp-admin
Download-URL: https://github.com/aio-libs/aiohttp-admin
License: Apache 2
Classifier: License :: OSI Approved :: Apache Software License
Classifier: Intended Audience :: Developers
Classifier: Programming Language :: Python :: 3
Classifier: Development Status :: 3 - Alpha
Classifier: Topic :: Internet :: WWW/HTTP
Classifier: Framework :: AsyncIO
Classifier: Framework :: aiohttp
License-File: LICENSE
Requires-Dist: aiohttp >=3.9
Requires-Dist: aiohttp-security
Requires-Dist: aiohttp-session
Requires-Dist: cryptography
Requires-Dist: pydantic <3,>2
Requires-Dist: typing-extensions >=3.10 ; python_version < "3.12"
Provides-Extra: sa
Requires-Dist: sqlalchemy <3,>=2.0.4 ; extra == 'sa'
